LICENSE
MANIFEST.in
README.rst
doc-requirements.txt
requirements.txt
setup.cfg
setup.py
test-requirements.txt
versioneer.py
scripttester/__init__.py
scripttester/_version.py
scripttester/scripttester.py
scripttester.egg-info/PKG-INFO
scripttester.egg-info/SOURCES.txt
scripttester.egg-info/dependency_links.txt
scripttester.egg-info/requires.txt
scripttester.egg-info/top_level.txt
scripttester/tests/conftest.py
scripttester/tests/test_mypkg66.py
scripttester/tests/mypkg66/setup.py
scripttester/tests/mypkg66/mypkg66/__init__.py
scripttester/tests/mypkg66/scripts/mypkg66_script